rouskinhf/__init__.py
rouskinhf/conversion.py
rouskinhf/datapoint.py
rouskinhf/env.py
rouskinhf/filter.py
rouskinhf/hf.py
rouskinhf/list_datapoints.py
rouskinhf/parsers.py
rouskinhf/path.py
rouskinhf/rnastructure.py
rouskinhf/test.py
rouskinhf/util.py
rouskinhf-0.4.8.dist-info/LICENSE
rouskinhf-0.4.8.dist-info/METADATA
rouskinhf-0.4.8.dist-info/WHEEL
rouskinhf-0.4.8.dist-info/top_level.txt
rouskinhf-0.4.8.dist-info/RECORD
