Metadata-Version: 2.1
Name: rouskinhf
Version: 0.4.8
Summary: A library to manipulate data for our DMS prediction models.
Author-email: Yves Martin <yves@martin.yt>, Alberic de Lajarte <albericlajarte@gmail.com>
License: MIT License
Classifier: Development Status :: 3 - Alpha
Classifier: Intended Audience :: Developers
Classifier: Programming Language :: Python :: 3.10
Requires-Python: >=3.10
License-File: LICENSE
